.editorconfig
.gitignore
.gitlab-ci.yml
README.rst
publish.settings.sh
publish.sh
pyproject.toml
tsconfig.json
.idea/modules.xml
.idea/peek-core-search.iml
.idea/inspectionProfiles/Project_Default.xml
.idea/inspectionProfiles/profiles_settings.xml
peek_core_search/PlatformDependencyTest.py
peek_core_search/__init__.py
peek_core_search/plugin_package.json
peek_core_search.egg-info/PKG-INFO
peek_core_search.egg-info/SOURCES.txt
peek_core_search.egg-info/dependency_links.txt
peek_core_search.egg-info/requires.txt
peek_core_search.egg-info/top_level.txt
peek_core_search/_private/PluginNames.py
peek_core_search/_private/__init__.py
peek_core_search/_private/alembic.ini
peek_core_search/_private/admin-app/search.module.ts
peek_core_search/_private/admin-app/components/edit-exclude-search-term-table/edit.component.html
peek_core_search/_private/admin-app/components/edit-exclude-search-term-table/edit.component.ts
peek_core_search/_private/admin-app/components/edit-object-type-table/edit.component.html
peek_core_search/_private/admin-app/components/edit-object-type-table/edit.component.ts
peek_core_search/_private/admin-app/components/edit-property-table/edit.component.html
peek_core_search/_private/admin-app/components/edit-property-table/edit.component.ts
peek_core_search/_private/admin-app/components/edit-setting-table/edit.component.html
peek_core_search/_private/admin-app/components/edit-setting-table/edit.component.ts
peek_core_search/_private/admin-app/components/search-page/search-page.component.html
peek_core_search/_private/admin-app/components/search-page/search-page.component.scss
peek_core_search/_private/admin-app/components/search-page/search-page.component.ts
peek_core_search/_private/admin-app/components/status-component/status.component.html
peek_core_search/_private/admin-app/components/status-component/status.component.scss
peek_core_search/_private/admin-app/components/status-component/status.component.ts
peek_core_search/_private/admin-app/tuples/ExcludeSearchStringTable.ts
peek_core_search/_private/agent/AgentEntryHook.py
peek_core_search/_private/agent/__init__.py
peek_core_search/_private/alembic/__init__.py
