Metadata-Version: 2.4
Name: peek-core-search
Version: 5.0.4
Summary: Peek Plugin Search - search support for Peek
Author-email: Synerty <contact@synerty.com>
Project-URL: Homepage, https://github.com/Synerty/peek-core-search
Keywords: Peek,Python,Platform,synerty
Requires-Dist: peek-plugin-base==5.0.4
Requires-Dist: peek_abstract_chunked_index==5.0.4
